cli/__init__.py
cli/__main__.py
solver/__init__.py
solver/ast.py
solver/aws.py
solver/errors.py
solver/teleport.py
solver/test/__init__.py
solver/test/test_ast.py
solver/test/test_aws.py
solver/test/test_teleport.py
solver/test/test_teleport_access_requests.py
solver/test/test_teleport_get_started.py
predicate_dev_test-0.1.0.dist-info/entry_points.txt
predicate_dev_test-0.1.0.dist-info/WHEEL
predicate_dev_test-0.1.0.dist-info/METADATA
predicate_dev_test-0.1.0.dist-info/RECORD
