Metadata-Version: 2.1
Name: predicate-dev-test
Version: 0.1.0
Summary: 
Author: Sakshyam Shah
Author-email: sshah@goteleport.com
Requires-Python: >=3.10,<4.0
Classifier: Programming Language :: Python :: 3
Classifier: Programming Language :: Python :: 3.10
Classifier: Programming Language :: Python :: 3.11
Requires-Dist: PyYAML (>=6.0,<7.0)
Requires-Dist: black (>=22.8.0,<23.0.0)
Requires-Dist: click (>=8.1.3,<9.0.0)
Requires-Dist: flake8 (>=5.0.4,<6.0.0)
Requires-Dist: isort (>=5.10.1,<6.0.0)
Requires-Dist: lint-python (>=2.0.0,<3.0.0)
Requires-Dist: mypy (>=0.982,<0.983)
Requires-Dist: pytest (>=7.1.3,<8.0.0)
Requires-Dist: setuptools (>=65.3.0,<66.0.0)
Requires-Dist: z3-solver (>=4.11.2.0,<5.0.0.0)
